{
  "id": 3,
  "description": "Selecciona la respuesta correcta. Lee detenidamente las preguntas o afirmaciones y selecciona la respuesta correcta en cada caso.",
	"type": "multiple",
  "mode":"IXT",
	"score": 3,
	"questions": [
        {
            "id": 0,
            "description": "El órgano que ves en pantalla es: ",
            "imagen": "./assets/img/actividades/nervioso/cerebro.svg",
            "options": [
                {
                  "id": 1,
                  "description": "Médula espinal",
                  "imagen": ""
                },
                {
                  "id": 2,
                  "description": "Cerebro",
                  "imagen": ""
                },
                {
                  "id": 3,
                  "description": "Nervios",
                  "imagen": ""
                }
            ],
            "answer": 1,
            "score": 1
        },
        {
            "id": 1,
            "description": "Este órgano sirve de soporte al cuerpo.",
            "imagen": "",
            "options": [
                {
                  "id": 1,
                  "description": "Médula espinal",
                  "imagen": ""
                },
                {
                  "id": 2,
                  "description": "Cerebro",
                  "imagen": ""
                },
                {
                  "id": 3,
                  "description": "Nervios",
                  "imagen": ""
                }
            ],
            "answer": 1,
            "score": 1
        },
        {
            "id": 2,
            "description": "Son cables que envían señales al cerebro.",
            "imagen": "",
            "options": [
                {
                  "id": 1,
                  "description": "Médula espinal",
                  "imagen": ""
                },
                {
                  "id": 2,
                  "description": "Cerebro",
                  "imagen": ""
                },
                {
                  "id": 3,
                  "description": "Nervios",
                  "imagen": ""
                }
            ],
            "answer": 3,
            "score": 1
        }
    ]
}